setup.cfg
setup.py
distributions/Binomialdistribution.py
distributions/Gaussiandistribution.py
distributions/Generaldistribution.py
distributions/__init__.py
distributionsefehan.egg-info/PKG-INFO
distributionsefehan.egg-info/SOURCES.txt
distributionsefehan.egg-info/dependency_links.txt
distributionsefehan.egg-info/not-zip-safe
distributionsefehan.egg-info/top_level.txt