Metadata-Version: 1.0
Name: distributionsefehan
Version: 0.5
Summary: Gaussian distributions
Home-page: UNKNOWN
Author: Efehan Danisman
Author-email: efedanisman@gmail.com
License: UNKNOWN
Platform: UNKNOWN
